{
    "id": 138366513,
    "name": "v420per challenge X",
    "author": "cuneiformality",
    "creators": [],
    "verifier": "cuneiformality",
    "verification": "https://youtu.be/pNRWHu0Zq24?si=lbWIoLNqasVdvSFA",
    "percentToQualify": "70",
    "enjoyment":7,
    "difficulty":2,
    "description": "When You.... Find Meee",
    "tags": [
        "2.2",
        "medium",
        "wave",
        "chokepoints",
        "timings"
    ],
    "records": [
        {
            "user": "Patat",
            "link": "https://youtu.be/pNRWHu0Zq24?si=lbWIoLNqasVdvSFA",
            "percent": 100,
            "hz": 240
        },
        {
            "user": "Metronite",
            "link": "https://medal.tv/games/geometry-dash/clips/mHdImp6YZxkfMYxiA?invite=cr-MSxLOE0sNDQ2ODY3MjM5&v=37",
            "percent": 100,
            "enjoyment":8,
            "hz": 240
        },
        {
            "user": "Cross",
            "link": "https://youtu.be/EDa-v8Zsf3o",
            "percent": 100,
            "enjoyment":2,
            "hz": 240
        },
        {
            "user": "DiamondNovabeast",
            "link": "https://youtu.be/CfziblC3qns",
            "percent": 100,
            "enjoyment":6,
            "hz": 240
        },
        {
            "user": "typher",
            "link": "https://drive.google.com/file/d/1u2yrqfh6yYJAcVD8G0IJdykgEtbfGxkV/view?usp=drive_link",
            "percent": 100,
            "enjoyment":5,
            "hz": 240
        }
    ]
}