{
    "id": 110610070,
    "name": "Wavescapes",
    "author": "EthanDemon",
    "creators": [],
    "verifier": "EthanDemon",
    "verification": "https://youtu.be/Ahc6GORQOnc?si=d3Q9p6maKouw9G4W",
    "percentToQualify": "69",
    "enjoyment":10,
    "difficulty":1,
    "description": "A Nullscapes-inspired level opting to use mainly the wave gamemode instead of the robot gamemode.",
    "tags": [
        "2.2",
        "medium",
        "wave",
        "chokepoints"
    ],
    "records": [
        {
            "user": "Patat",
            "link": "https://youtu.be/UXrZ0WLaHls",
            "percent": 100,
            "hz": 240
        },
        {
            "user": "DiamondNovabeast",
            "link": "https://youtu.be/W9trJHATHgQ",
            "percent": 100,
            "enjoyment":7,
            "hz": 240
        },
        {
            "user": "Cross",
            "link": "https://www.youtube.com/watch?v=vOhOAlBQ5vk",
            "percent": 100,
            "enjoyment":9,
            "hz": 240
        }
    ]
}
